msdparser/__init__.py
msdparser/lexer.py
msdparser/parameter.py
msdparser/parser.py
msdparser/py.typed
msdparser-2.0.0.dist-info/LICENSE.md
msdparser-2.0.0.dist-info/METADATA
msdparser-2.0.0.dist-info/WHEEL
msdparser-2.0.0.dist-info/top_level.txt
msdparser-2.0.0.dist-info/RECORD
