Metadata-Version: 2.1
Name: msdparser
Version: 2.0.0
Summary: Robust & lightning fast MSD parser (StepMania file format)
Home-page: http://github.com/garcia/msdparser
Author: Ash Garcia
Author-email: python-msdparser@garcia.sh
License: MIT
Keywords: stepmania simfile sm ssc dwi
Platform: UNKNOWN
Classifier: Development Status :: 5 - Production/Stable
Classifier: Programming Language :: Python :: 3
Classifier: Topic :: Games/Entertainment
Classifier: Topic :: Software Development :: Libraries :: Python Modules
Classifier: Typing :: Typed
Requires-Python: >=3.6
